emblio/__init__.py
emblio/embedding.py
emblio/embedding_new.py
emblio/example.py
emblio/whisper.py
emblio-0.1.1.dist-info/LICENSE
emblio-0.1.1.dist-info/METADATA
emblio-0.1.1.dist-info/WHEEL
emblio-0.1.1.dist-info/top_level.txt
emblio-0.1.1.dist-info/RECORD
