Metadata-Version: 2.1
Name: emblio
Version: 0.1.1
Summary: python package that gets embeddings from various ML models for  different content types, like image video audio text
Home-page: https://github.com/nishantb06/emblio
Author: Nishant Bhansali
Author-email: nishantbhansali80@gmail.com
License: MIT
Classifier: Development Status :: 2 - Pre-Alpha
Classifier: License :: OSI Approved :: MIT License
Classifier: Programming Language :: Python
Classifier: Programming Language :: Python :: 2
Classifier: Programming Language :: Python :: 2.7
Classifier: Programming Language :: Python :: 3
Classifier: Programming Language :: Python :: 3.4
Classifier: Programming Language :: Python :: 3.5
Classifier: Programming Language :: Python :: 3.6
Classifier: Programming Language :: Python :: 3.7
License-File: LICENSE
